[{"name": "Youssef Germain", "morningOptionIndex": 1, "eveningOptionIndex": 2}, {"name": "Johnny Mercier", "morningOptionIndex": 4, "eveningOptionIndex": 4}, {"name": "Mario Aubert", "morningOptionIndex": 2, "eveningOptionIndex": 3}, {"name": "Mathias Poulain", "morningOptionIndex": 3, "eveningOptionIndex": 1}, {"name": "Lia Boyer", "morningOptionIndex": 2, "eveningOptionIndex": 1}, {"name": "Magaly Lambert", "morningOptionIndex": 0, "eveningOptionIndex": 3}, {"name": "Natanael Berger", "morningOptionIndex": 2, "eveningOptionIndex": 0}, {"name": "Mohammad Schmitt", "morningOptionIndex": 2, "eveningOptionIndex": 2}, {"name": "Alexandra Dufour", "morningOptionIndex": 0, "eveningOptionIndex": 0}, {"name": "Nadege Deschamps", "morningOptionIndex": 0, "eveningOptionIndex": 1}, {"name": "Elisa Guillot", "morningOptionIndex": 1, "eveningOptionIndex": 0}, {"name": "Armando Chevallier", "morningOptionIndex": 1, "eveningOptionIndex": 0}, {"name": "Mounir Marechal", "morningOptionIndex": 1, "eveningOptionIndex": 1}, {"name": "Danny Adam", "morningOptionIndex": 0, "eveningOptionIndex": 2}, {"name": "Achille Poulain", "morningOptionIndex": 1, "eveningOptionIndex": 1}, {"name": "Anna Menard", "morningOptionIndex": 0, "eveningOptionIndex": 1}, {"name": "Pascale Joly", "morningOptionIndex": 1, "eveningOptionIndex": 0}, {"name": "Marthe Brun", "morningOptionIndex": 0, "eveningOptionIndex": 0}, {"name": "Luis Rousseau", "morningOptionIndex": 3, "eveningOptionIndex": 2}, {"name": "Gwendoline Meyer", "morningOptionIndex": 2, "eveningOptionIndex": 0}, {"name": "MarieJosee Jacquet", "morningOptionIndex": 4, "eveningOptionIndex": 0}, {"name": "Filippo Durand", "morningOptionIndex": 1, "eveningOptionIndex": 1}, {"name": "Sidonie Weber", "morningOptionIndex": 0, "eveningOptionIndex": 0}, {"name": "Yohann Bouvier", "morningOptionIndex": 1, "eveningOptionIndex": 0}, {"name": "Gordon Leroux", "morningOptionIndex": 0, "eveningOptionIndex": 2}, {"name": "Helena Leveque", "morningOptionIndex": 0, "eveningOptionIndex": 2}, {"name": "Tito Le gall", "morningOptionIndex": 2, "eveningOptionIndex": 1}, {"name": "Laurie Adam", "morningOptionIndex": 2, "eveningOptionIndex": 0}, {"name": "Brahim Duval", "morningOptionIndex": 0, "eveningOptionIndex": 3}, {"name": "Nina Gillet", "morningOptionIndex": 2, "eveningOptionIndex": 1}, {"name": "Fritz Albert", "morningOptionIndex": 0, "eveningOptionIndex": 2}, {"name": "Maria Boyer", "morningOptionIndex": 2, "eveningOptionIndex": 1}, {"name": "Pascaline Huet", "morningOptionIndex": 2, "eveningOptionIndex": 0}, {"name": "Nina Fleury", "morningOptionIndex": 3, "eveningOptionIndex": 0}, {"name": "Carmine Albert", "morningOptionIndex": 0, "eveningOptionIndex": 0}, {"name": "Nina Thomas", "morningOptionIndex": 1, "eveningOptionIndex": 0}, {"name": "Bianca Aubry", "morningOptionIndex": 0, "eveningOptionIndex": 4}, {"name": "Leonie Picard", "morningOptionIndex": 1, "eveningOptionIndex": 0}, {"name": "Gunter Adam", "morningOptionIndex": 3, "eveningOptionIndex": 1}, {"name": "Cerise Durand", "morningOptionIndex": 1, "eveningOptionIndex": 1}, {"name": "Ralf Guillot", "morningOptionIndex": 3, "eveningOptionIndex": 2}, {"name": "Bernhard Sanchez", "morningOptionIndex": 3, "eveningOptionIndex": 1}, {"name": "Angelina Mercier", "morningOptionIndex": 1, "eveningOptionIndex": 1}, {"name": "MarieJosee Renault", "morningOptionIndex": 0, "eveningOptionIndex": 3}, {"name": "Fabre David", "morningOptionIndex": 1, "eveningOptionIndex": 1}, {"name": "Gisele Olivier", "morningOptionIndex": 0, "eveningOptionIndex": 1}, {"name": "Vivian Paris", "morningOptionIndex": 1, "eveningOptionIndex": 0}, {"name": "Fabienne Roy", "morningOptionIndex": 1, "eveningOptionIndex": 3}, {"name": "Tonia Mathieu", "morningOptionIndex": 1, "eveningOptionIndex": 4}, {"name": "Zoubida Albert", "morningOptionIndex": 4, "eveningOptionIndex": 2}, {"name": "Jeremy Klein", "morningOptionIndex": 0, "eveningOptionIndex": 0}, {"name": "Claire Gonzalez", "morningOptionIndex": 0, "eveningOptionIndex": 0}]